rtcomm/__init__.py
rtcomm/client/__init__.py
rtcomm/client/sdk.py
rtcomm/core/__init__.py
rtcomm/core/config.py
rtcomm/core/constants.py
rtcomm/core/prompts.py
rtcomm/data/__init__.py
rtcomm/data/interim/__init__.py
rtcomm/data/processed/__init__.py
rtcomm/data/raw/__init__.py
rtcomm/handlers/__init__.py
rtcomm/handlers/custom_exceptions.py
rtcomm/handlers/output_generator.py
rtcomm/hub/__init__.py
rtcomm/hub/base.py
rtcomm/hub/manager.py
rtcomm/models/__init__.py
rtcomm/protocol/__init__.py
rtcomm/protocol/messages.py
rtcomm/schemas/__init__.py
rtcomm/schemas/config_schema.py
rtcomm/services/__init__.py
rtcomm/services/langchain_framework.py
rtcomm/utils/__init__.py
rtcomm/utils/custom_logging.py
rtcomm/utils/helper_functions.py
rtcomm-0.0.1.dist-info/licenses/LICENSE
rtcomm-0.0.1.dist-info/METADATA
rtcomm-0.0.1.dist-info/WHEEL
rtcomm-0.0.1.dist-info/top_level.txt
rtcomm-0.0.1.dist-info/RECORD
