Metadata-Version: 2.4
Name: rtcomm
Version: 0.0.1
Summary: A scalable, distributed real-time communication hub using WebSockets and JSON encoding, inspired by SignalR.
Author-email: MusaddiqueHussain Jahagirdar <musaddiquehussainlabs@gmail.com>
Maintainer-email: MusaddiqueHussain Jahagirdar <musaddiquehussainlabs@gmail.com>
Project-URL: Homepage, https://github.com/MusaddiqueHussainLabs/rtcomm_package
Project-URL: Documentation, https://github.com/MusaddiqueHussainLabs/rtcomm_package/wiki
Project-URL: Source, https://github.com/MusaddiqueHussainLabs/rtcomm_package
Project-URL: Issues, https://github.com/MusaddiqueHussainLabs/rtcomm_package/issues
Keywords: WebSocket,SignalR,real-time,FastAPI,RTComm,pubsub
Classifier: Development Status :: 3 - Alpha
Classifier: Intended Audience :: Developers
Classifier: Topic :: Communications :: Chat
Classifier: Topic :: Internet :: WWW/HTTP :: WSGI :: Server
Classifier: Framework :: AsyncIO
Classifier: License :: OSI Approved :: MIT License
Classifier: Operating System :: OS Independent
Classifier: Intended Audience :: Developers
Classifier: Programming Language :: Python :: 3
Classifier: Programming Language :: Python :: 3.9
Classifier: Programming Language :: Python :: 3.10
Classifier: Programming Language :: Python :: 3.11
Requires-Python: >=3.9
License-File: LICENSE
Requires-Dist: fastapi>=0.100.0
Requires-Dist: websockets>=11.0.0
Requires-Dist: pydantic>=2.0
Requires-Dist: uvicorn[standard]>=0.23.0
Dynamic: license-file
